odoo/addons/l10n_de_steuernummer/README.rst
odoo/addons/l10n_de_steuernummer/__init__.py
odoo/addons/l10n_de_steuernummer/__manifest__.py
odoo/addons/l10n_de_steuernummer/i18n/de.po
odoo/addons/l10n_de_steuernummer/i18n/fr.po
odoo/addons/l10n_de_steuernummer/i18n/l10n_de_steuernummer.pot
odoo/addons/l10n_de_steuernummer/models/__init__.py
odoo/addons/l10n_de_steuernummer/models/res_partner.py
odoo/addons/l10n_de_steuernummer/static/description/icon.png
odoo/addons/l10n_de_steuernummer/tests/__init__.py
odoo/addons/l10n_de_steuernummer/tests/test_l10n_de_steuernummer.py
odoo11_addon_l10n_de_steuernummer-11.0.1.0.0.99.dev3.dist-info/METADATA
odoo11_addon_l10n_de_steuernummer-11.0.1.0.0.99.dev3.dist-info/RECORD
odoo11_addon_l10n_de_steuernummer-11.0.1.0.0.99.dev3.dist-info/WHEEL
odoo11_addon_l10n_de_steuernummer-11.0.1.0.0.99.dev3.dist-info/top_level.txt
